mapdl_archive-0.2.7.dist-info/RECORD
mapdl_archive-0.2.7.dist-info/WHEEL
mapdl_archive-0.2.7.dist-info/METADATA
mapdl_archive-0.2.7.dist-info/licenses/LICENSE
mapdl_archive/_archive.abi3.so
mapdl_archive/_reader.abi3.so
mapdl_archive/elements.py
mapdl_archive/__init__.py
mapdl_archive/mesh.py
mapdl_archive/_archive.pyi
mapdl_archive/archive.py
mapdl_archive/py.typed
mapdl_archive/_reader.pyi
mapdl_archive/examples/TetBeam.cdb
mapdl_archive/examples/academic_rotor.cdb
mapdl_archive/examples/HexBeam.cdb
mapdl_archive/examples/__init__.py
mapdl_archive/examples/examples.py
mapdl_archive/examples/sector.cdb
