Metadata-Version: 2.1
Name: mapdl-archive
Version: 0.2.7
Summary: Pythonic interface to MAPDL archive files.
Author-Email: Alex Kaszynski <akascap@gmail.com>
Classifier: Development Status :: 4 - Beta
Classifier: Intended Audience :: Science/Research
Classifier: Topic :: Scientific/Engineering :: Information Analysis
Classifier: License :: OSI Approved :: MIT License
Classifier: Operating System :: Microsoft :: Windows
Classifier: Operating System :: POSIX
Classifier: Operating System :: MacOS
Classifier: Programming Language :: Python :: 3.9
Classifier: Programming Language :: Python :: 3.10
Classifier: Programming Language :: Python :: 3.11
Classifier: Programming Language :: Python :: 3.12
Classifier: Programming Language :: Python :: 3.13
Project-URL: Repository, https://github.com/akaszynski/mapdl-archive
Requires-Python: >=3.9
Requires-Dist: pyvista>=0.41.1
